Workbook

Sheet Dashboard
A1: EXECUTIVE DASHBOARD
A15: Total Estimated Cost: | B15: =Costing_Engine!H7
A16: Total Quote Price: | B16: =Costing_Engine!H8
A17: Estimated Profit: | B17: =B16-B15
A20: Category | B20: Cost | D20: Metric | E20: Value
A21: Material | B21: =Costing_Engine!H2 | D21: Prime Cost | E21: =Costing_Engine!H7
A22: Labor | B22: =Costing_Engine!H3 | D22: Total Quote | E22: =Costing_Engine!H8
A23: Overheads | B23: =Costing_Engine!H4 + Costing_Engine!H6

Sheet Material_DB
A1: Part Number | B1: Description | C1: Unit | D1: Unit Cost | E1: Category
A2: MAT-001 | B2: Steel Sheet 2mm | C2: m2 | D2: 25.5 | E2: Raw Material
A3: MAT-002 | B3: Aluminum Rod 10mm | C3: m | D3: 12 | E3: Raw Material
A4: MAT-003 | B4: Copper Wire | C4: m | D4: 8.75 | E4: Electrical
A5: MAT-004 | B5: Plastic Housing | C5: pcs | D5: 5.2 | E5: Components

Sheet Labor_Machine_DB
A1: Role/Machine | B1: Hourly Rate | C1: Burden % | D1: Total Hourly Cost
A2: Senior Technician | B2: 45 | C2: 0.25 | D2: 56.25
A3: Junior Operator | B3: 25 | C3: 0.2 | D3: 30
A4: CNC Machine | B4: 80 | C4: 0.15 | D4: 92
A5: Assembly Line | B5: 15 | C5: 0.1 | D5: 16.5

Sheet Settings
A1: Parameter | B1: Value | C1: Description
A2: Target Margin % | B2: 0.2 | C2: Desired profit margin
A3: Manufacturing Overhead % | B3: 0.15 | C3: Applied to direct costs
A4: Admin/Sales Overhead % | B4: 0.1 | C4: Applied to production costs
A5: Tax Rate % | B5: 0.08 | C5: Sales tax
A6: Currency | B6: USD | C6: Base currency

Sheet Costing_Engine
A1: Category | B1: Item Name | C1: Quantity/Hours | D1: Unit Rate | E1: Total Cost | F1: Notes | G1: Cost Summary
A2: Material | B2: Steel Sheet 2mm | C2: 10 | D2: =IFERROR(IF(A2="Material", XLOOKUP(B2, Material_DB!B:B, Material_DB!D:D, 0), XLOOKUP(B2, Labor_Machine_DB!A:A, Labor_Machine_DB!D:D, 0)), 0) | E2: =IFERROR(C2*D2, 0) | G2: Total Direct Material | H2: =SUMIF(A:A, "Material", E:E)
A3: Labor | B3: Senior Technician | C3: 5 | D3: =IFERROR(IF(A3="Material", XLOOKUP(B3, Material_DB!B:B, Material_DB!D:D, 0), XLOOKUP(B3, Labor_Machine_DB!A:A, Labor_Machine_DB!D:D, 0)), 0) | E3: =IFERROR(C3*D3, 0) | G3: Total Direct Labor | H3: =SUMIF(A:A, "Labor", E:E)
D4: =IFERROR(IF(A4="Material", XLOOKUP(B4, Material_DB!B:B, Material_DB!D:D, 0), XLOOKUP(B4, Labor_Machine_DB!A:A, Labor_Machine_DB!D:D, 0)), 0) | E4: =IFERROR(C4*D4, 0) | G4: Manufacturing Overhead | H4: =(H2+H3)*Settings!$B$3
D5: =IFERROR(IF(A5="Material", XLOOKUP(B5, Material_DB!B:B, Material_DB!D:D, 0), XLOOKUP(B5, Labor_Machine_DB!A:A, Labor_Machine_DB!D:D, 0)), 0) | E5: =IFERROR(C5*D5, 0) | G5: Total Production Cost | H5: =H2+H3+H4
D6: =IFERROR(IF(A6="Material", XLOOKUP(B6, Material_DB!B:B, Material_DB!D:D, 0), XLOOKUP(B6, Labor_Machine_DB!A:A, Labor_Machine_DB!D:D, 0)), 0) | E6: =IFERROR(C6*D6, 0) | G6: Admin/Sales Overhead | H6: =H5*Settings!$B$4
D7: =IFERROR(IF(A7="Material", XLOOKUP(B7, Material_DB!B:B, Material_DB!D:D, 0), XLOOKUP(B7, Labor_Machine_DB!A:A, Labor_Machine_DB!D:D, 0)), 0) | E7: =IFERROR(C7*D7, 0) | G7: Prime Cost | H7: =H5+H6
D8: =IFERROR(IF(A8="Material", XLOOKUP(B8, Material_DB!B:B, Material_DB!D:D, 0), XLOOKUP(B8, Labor_Machine_DB!A:A, Labor_Machine_DB!D:D, 0)), 0) | E8: =IFERROR(C8*D8, 0) | G8: Final Quote Price | H8: =H7/(1-Settings!$B$2)
D9: =IFERROR(IF(A9="Material", XLOOKUP(B9, Material_DB!B:B, Material_DB!D:D, 0), XLOOKUP(B9, Labor_Machine_DB!A:A, Labor_Machine_DB!D:D, 0)), 0) | E9: =IFERROR(C9*D9, 0) | G9: Margin Check | H9: =IF(Settings!B2<0.1, "LOW MARGIN WARNING", "Margin OK")
D10: =IFERROR(IF(A10="Material", XLOOKUP(B10, Material_DB!B:B, Material_DB!D:D, 0), XLOOKUP(B10, Labor_Machine_DB!A:A, Labor_Machine_DB!D:D, 0)), 0) | E10: =IFERROR(C10*D10, 0)
D11: =IFERROR(IF(A11="Material", XLOOKUP(B11, Material_DB!B:B, Material_DB!D:D, 0), XLOOKUP(B11, Labor_Machine_DB!A:A, Labor_Machine_DB!D:D, 0)), 0) | E11: =IFERROR(C11*D11, 0)
D12: =IFERROR(IF(A12="Material", XLOOKUP(B12, Material_DB!B:B, Material_DB!D:D, 0), XLOOKUP(B12, Labor_Machine_DB!A:A, Labor_Machine_DB!D:D, 0)), 0) | E12: =IFERROR(C12*D12, 0)
D13: =IFERROR(IF(A13="Material", XLOOKUP(B13, Material_DB!B:B, Material_DB!D:D, 0), XLOOKUP(B13, Labor_Machine_DB!A:A, Labor_Machine_DB!D:D, 0)), 0) | E13: =IFERROR(C13*D13, 0)
D14: =IFERROR(IF(A14="Material", XLOOKUP(B14, Material_DB!B:B, Material_DB!D:D, 0), XLOOKUP(B14, Labor_Machine_DB!A:A, Labor_Machine_DB!D:D, 0)), 0) | E14: =IFERROR(C14*D14, 0)
D15: =IFERROR(IF(A15="Material", XLOOKUP(B15, Material_DB!B:B, Material_DB!D:D, 0), XLOOKUP(B15, Labor_Machine_DB!A:A, Labor_Machine_DB!D:D, 0)), 0) | E15: =IFERROR(C15*D15, 0)
D16: =IFERROR(IF(A16="Material", XLOOKUP(B16, Material_DB!B:B, Material_DB!D:D, 0), XLOOKUP(B16, Labor_Machine_DB!A:A, Labor_Machine_DB!D:D, 0)), 0) | E16: =IFERROR(C16*D16, 0)
D17: =IFERROR(IF(A17="Material", XLOOKUP(B17, Material_DB!B:B, Material_DB!D:D, 0), XLOOKUP(B17, Labor_Machine_DB!A:A, Labor_Machine_DB!D:D, 0)), 0) | E17: =IFERROR(C17*D17, 0)
D18: =IFERROR(IF(A18="Material", XLOOKUP(B18, Material_DB!B:B, Material_DB!D:D, 0), XLOOKUP(B18, Labor_Machine_DB!A:A, Labor_Machine_DB!D:D, 0)), 0) | E18: =IFERROR(C18*D18, 0)
D19: =IFERROR(IF(A19="Material", XLOOKUP(B19, Material_DB!B:B, Material_DB!D:D, 0), XLOOKUP(B19, Labor_Machine_DB!A:A, Labor_Machine_DB!D:D, 0)), 0) | E19: =IFERROR(C19*D19, 0)
D20: =IFERROR(IF(A20="Material", XLOOKUP(B20, Material_DB!B:B, Material_DB!D:D, 0), XLOOKUP(B20, Labor_Machine_DB!A:A, Labor_Machine_DB!D:D, 0)), 0) | E20: =IFERROR(C20*D20, 0)
D21: =IFERROR(IF(A21="Material", XLOOKUP(B21, Material_DB!B:B, Material_DB!D:D, 0), XLOOKUP(B21, Labor_Machine_DB!A:A, Labor_Machine_DB!D:D, 0)), 0) | E21: =IFERROR(C21*D21, 0)
... D100: =IFERROR(IF(A100="Material", XLOOKUP(B100, Material_DB!B:B, Material_DB!D:D, 0), XLOOKUP(B100, Labor_Machine_DB!A:A, Labor_Machine_DB!D:D, 0)), 0) | E100: =IFERROR(C100*D100, 0)

Sheet Quote_Summary
A1: MANUFACTURING QUOTE | B1: Details | C1: Amount
A3: Description | B3: Amount
A4: Total Production Cost | B4: =Costing_Engine!H5
A5: Overheads & Admin | B5: =Costing_Engine!H6
A6: Profit Margin | B6: =B7-Costing_Engine!H7
A7: TOTAL QUOTE PRICE | B7: =Costing_Engine!H8
