Workbook

Sheet Dashboard
A1: 📈 MANUFACTURING COST DASHBOARD
A3: Selected Product: | B3: ="Cost Summary"!B3 -> #VALUE! | C3: ="Cost Summary"!D3 -> #VALUE!
A5: KEY PERFORMANCE INDICATORS
A6: Total Unit Cost: | B6: ="Cost Summary"!C22 -> #VALUE!
A7: Selling Price: | B7: ="Cost Summary"!B30 -> #VALUE!
A8: Gross Margin: | B8: ="Cost Summary"!B32 -> #VALUE!
A9: BOM Cost %: | B9: =IFERROR("Cost Summary"!C7/"Cost Summary"!C22,0) -> #VALUE!
A10: Labor Cost %: | B10: =IFERROR("Cost Summary"!C8/"Cost Summary"!C22,0) -> #VALUE!
A13: COST BREAKDOWN DATA
A14: Category | B14: Cost
A15: Materials | B15: ="Cost Summary"!C7 -> #VALUE!
A16: Labor | B16: ="Cost Summary"!C8 -> #VALUE!
A17: Machines | B17: ="Cost Summary"!C9 -> #VALUE!
A18: Tooling | B18: ="Cost Summary"!C10 -> #VALUE!
A19: Quality | B19: ="Cost Summary"!C11 -> #VALUE!
A20: Packaging | B20: ="Cost Summary"!C12 -> #VALUE!
A21: Logistics | B21: ="Cost Summary"!C13 -> #VALUE!
A22: Overhead | B22: ="Cost Summary"!C20 -> #VALUE!
A26: SUPPLIER PERFORMANCE
A27: Supplier | B27: Quality Rating | C27: Reliability | D27: Lead Time
A28: =Suppliers!B4 -> Alpha Manufacturing Co. | B28: =Suppliers!H4 -> 4.2 | C28: =Suppliers!I4 -> 4.5 | D28: =Suppliers!E4 -> 21
A29: =Suppliers!B5 -> Beta Components Ltd. | B29: =Suppliers!H5 -> 4.8 | C29: =Suppliers!I5 -> 4.9 | D29: =Suppliers!E5 -> 14
A30: =Suppliers!B6 -> Gamma Industries | B30: =Suppliers!H6 -> 3.8 | C30: =Suppliers!I6 -> 4 | D30: =Suppliers!E6 -> 28
A31: =Suppliers!B7 -> Delta Precision | B31: =Suppliers!H7 -> 4.5 | C31: =Suppliers!I7 -> 4.7 | D31: =Suppliers!E7 -> 7
A32: =Suppliers!B8 -> Epsilon Trading | B32: =Suppliers!H8 -> 4.6 | C32: =Suppliers!I8 -> 4.4 | D32: =Suppliers!E8 -> 18
A36: QUICK START GUIDE
A37: 1. Start with SETTINGS sheet - configure currencies, markup rates, and overhead percentages
A38: 2. Add your suppliers in the SUPPLIERS sheet with lead times and ratings
A39: 3. Define your products in the PRODUCTS sheet with SKU, name, and batch sizes
A40: 4. For each product, fill in the BOM with materials and supplier prices
A41: 5. Enter labor operations in LABOR sheet and machine operations in MACHINES sheet
A42: 6. Add tooling costs (NRE and recurring) in TOOLING sheet
A43: 7. Configure quality inspection requirements in QUALITY sheet
A44: 8. Set up packaging costs in PACKAGING sheet
A45: 9. Enter logistics/shipping options in LOGISTICS sheet
A46: 10. Review COST SUMMARY for complete cost rollup and pricing
A47: 11. Generate customer quotes in QUOTE sheet
A49: COLOR CODING: Blue = Input cells | Green text = Cross-sheet links | Yellow = Totals

Sheet Settings
A1: ⚙️ CONFIGURATION & SETTINGS
A3: CURRENCY SETTINGS
A4: Currency Code | B4: Currency Name | C4: Exchange Rate to USD | D4: Symbol
A5: USD | B5: US Dollar | C5: 1 | D5: $
A6: EUR | B6: Euro | C6: 1.085 | D6: €
A7: GBP | B7: British Pound | C7: 1.265 | D7: £
A8: CNY | B8: Chinese Yuan | C8: 0.138 | D8: ¥
A9: INR | B9: Indian Rupee | C9: 0.012 | D9: ₹
A10: JPY | B10: Japanese Yen | C10: 0.0067 | D10: ¥
A12: Base Currency: | B12: USD
A15: MARKUP & MARGIN SETTINGS
A16: Tier | B16: Quantity Range | C16: Markup % | D16: Effective Margin %
A17: Tier 1 - Low Volume | B17: 1 - 100 | C17: 0.35 | D17: =C17/(1+C17) -> 0.25925926
A18: Tier 2 - Medium Volume | B18: 101 - 500 | C18: 0.28 | D18: =C18/(1+C18) -> 0.21875
A19: Tier 3 - High Volume | B19: 501 - 1000 | C19: 0.22 | D19: =C19/(1+C19) -> 0.18032787
A20: Tier 4 - Bulk | B20: 1001+ | C20: 0.18 | D20: =C20/(1+C20) -> 0.15254237
A23: OVERHEAD ALLOCATION RATES
A24: Cost Category | B24: Allocation Method | C24: Rate/Percentage | D24: Notes
A25: Factory Overhead | B25: % of Direct Labor | C25: 0.85 | D25: Includes utilities, rent, supervision
A26: Administrative | B26: % of Total Direct Cost | C26: 0.12 | D26: G&A, HR, Finance
A27: Engineering Support | B27: % of Direct Labor | C27: 0.15 | D27: Design, process engineering
A28: Depreciation | B28: Per Machine Hour | C28: 25 | D28: Equipment depreciation rate
A31: QUALITY & INSPECTION RATES
A32: Inspection Type | B32: Rate
A33: Incoming Inspection | B33: 0.02
A34: In-Process Inspection | B34: 0.03
A35: Final Inspection | B35: 0.025
A36: Certification/Documentation | B36: 0.01

Sheet Suppliers
A1: 🏭 SUPPLIER DATABASE
A3: Supplier ID | B3: Supplier Name | C3: Country | D3: Currency | E3: Lead Time (Days) | F3: Payment Terms | G3: MOQ | H3: Quality Rating | I3: Reliability Score | J3: Status | K3: Contact | L3: Notes
A4: SUP001 | B4: Alpha Manufacturing Co. | C4: China | D4: CNY | E4: 21 | F4: Net 30 | G4: 500 | H4: 4.2 | I4: 4.5 | J4: Active | K4: john@alpha.cn | L4: Preferred for metals
A5: SUP002 | B5: Beta Components Ltd. | C5: Germany | D5: EUR | E5: 14 | F5: Net 45 | G5: 100 | H5: 4.8 | I5: 4.9 | J5: Active | K5: info@beta.de | L5: Premium quality
A6: SUP003 | B6: Gamma Industries | C6: India | D6: INR | E6: 28 | F6: Net 30 | G6: 1000 | H6: 3.8 | I6: 4 | J6: Active | K6: sales@gamma.in | L6: Cost effective
A7: SUP004 | B7: Delta Precision | C7: USA | D7: USD | E7: 7 | F7: Net 15 | G7: 50 | H7: 4.5 | I7: 4.7 | J7: Active | K7: order@delta.com | L7: Quick turnaround
A8: SUP005 | B8: Epsilon Trading | C8: Japan | D8: JPY | E8: 18 | F8: Net 60 | G8: 200 | H8: 4.6 | I8: 4.4 | J8: Active | K8: contact@epsilon.jp | L8: Electronics specialist
A9: SUP006
A10: SUP007
A11: SUP008

Sheet Products
A1: 📦 PRODUCT CATALOG
A3: SKU | B3: Product Name | C3: Category | D3: Unit | E3: Standard Qty | F3: Complexity | G3: Status | H3: Last Updated | I3: Notes
A4: SKU-001 | B4: Precision Gear Assembly | C4: Mechanical | D4: EA | E4: 100 | F4: High | G4: Active | H4: 2024-01-15 | I4: Custom machined
A5: SKU-002 | B5: Electronic Control Board | C5: Electronics | D5: EA | E5: 250 | F5: High | G5: Active | H5: 2024-01-10 | I5: SMT assembly
A6: SKU-003 | B6: Aluminum Housing - Large | C6: Enclosures | D6: EA | E6: 500 | F6: Medium | G6: Active | H6: 2024-01-08 | I6: Die cast
A7: SKU-004 | B7: Cable Assembly Kit | C7: Wiring | D7: SET | E7: 1000 | F7: Low | G7: Active | H7: 2024-01-05 | I7: Pre-assembled
A8: SKU-005 | B8: Stainless Steel Bracket | C8: Fabrication | D8: EA | E8: 200 | F8: Medium | G8: Active | H8: 2024-01-12 | I8: Laser cut + bent
A9: SKU-006
A10: SKU-007
A11: SKU-008

Sheet BOM
A1: 📋 BILL OF MATERIALS (BOM)
A3: Select SKU: | B3: SKU-001 | C3: Product Name: | D3: =IFERROR(VLOOKUP(B3,Products!A:B,2,FALSE()),"-") -> Precision Gear Assembly
A5: Item # | B5: Part Number | C5: Description | D5: Supplier 1 | E5: S1 Price | F5: S1 Currency | G5: Supplier 2 | H5: S2 Price | I5: S2 Currency | J5: Supplier 3 | K5: S3 Price | L5: S3 Currency | M5: Best Price (USD) | N5: Best Supplier | O5: Qty/Unit | P5: UOM | Q5: Extended Cost | R5: Lead Time
A6: 1 | B6: MTL-001 | C6: Steel Rod 10mm | D6: SUP001 | E6: 2.5 | F6: CNY | G6: SUP002 | H6: 0.45 | I6: EUR | J6: SUP004 | K6: 0.52 | L6: USD | M6: =IF(B6="","",MIN( IFERROR(E6*VLOOKUP(F6,Settings!$A$5:$C$10,3,FALSE()),9999999), IFERROR(H6*VLOOKUP(I6,Settings!$A$5:$C$10,3,FALSE()),9999999), IFERROR(K6*VLOOKUP(L6,Settings!$A$5:$C$10,3,FALSE()),9999999))) -> 0.345 | N6: =IF(B6="","",IF(M6=E6*VLOOKUP(F6,Settings!$A$5:$C$10,3,FALSE()),D6, IF(M6=H6*VLOOKUP(I6,Settings!$A$5:$C$10,3,FALSE()),G6,J6))) -> SUP001 | O6: M | Q6: =IF(B6="","",M6*O6) -> #VALUE! | R6: =IF(N6="","",IFERROR(VLOOKUP(N6,Suppliers!$A$4:$E$20,5,FALSE()),"-")) -> 21
A7: 2 | B7: MTL-002 | C7: Aluminum Sheet 2mm | D7: SUP001 | E7: 85 | F7: CNY | G7: SUP003 | H7: 950 | I7: INR | J7: SUP004 | K7: 15 | L7: USD | M7: =IF(B7="","",MIN( IFERROR(E7*VLOOKUP(F7,Settings!$A$5:$C$10,3,FALSE()),9999999), IFERROR(H7*VLOOKUP(I7,Settings!$A$5:$C$10,3,FALSE()),9999999), IFERROR(K7*VLOOKUP(L7,Settings!$A$5:$C$10,3,FALSE()),9999999))) -> 11.4 | N7: =IF(B7="","",IF(M7=E7*VLOOKUP(F7,Settings!$A$5:$C$10,3,FALSE()),D7, IF(M7=H7*VLOOKUP(I7,Settings!$A$5:$C$10,3,FALSE()),G7,J7))) -> SUP003 | O7: SQM | Q7: =IF(B7="","",M7*O7) -> #VALUE! | R7: =IF(N7="","",IFERROR(VLOOKUP(N7,Suppliers!$A$4:$E$20,5,FALSE()),"-")) -> 28
A8: 3 | B8: CMP-001 | C8: Bearing 6204-2RS | D8: SUP002 | E8: 3.2 | F8: EUR | G8: SUP005 | H8: 450 | I8: JPY | J8: SUP004 | K8: 4.1 | L8: USD | M8: =IF(B8="","",MIN( IFERROR(E8*VLOOKUP(F8,Settings!$A$5:$C$10,3,FALSE()),9999999), IFERROR(H8*VLOOKUP(I8,Settings!$A$5:$C$10,3,FALSE()),9999999), IFERROR(K8*VLOOKUP(L8,Settings!$A$5:$C$10,3,FALSE()),9999999))) -> 3.015 | N8: =IF(B8="","",IF(M8=E8*VLOOKUP(F8,Settings!$A$5:$C$10,3,FALSE()),D8, IF(M8=H8*VLOOKUP(I8,Settings!$A$5:$C$10,3,FALSE()),G8,J8))) -> SUP005 | O8: EA | Q8: =IF(B8="","",M8*O8) -> #VALUE! | R8: =IF(N8="","",IFERROR(VLOOKUP(N8,Suppliers!$A$4:$E$20,5,FALSE()),"-")) -> 18
A9: 4 | B9: CMP-002 | C9: M8 Hex Bolt Set | D9: SUP001 | E9: 0.8 | F9: CNY | G9: SUP003 | H9: 12 | I9: INR | J9: SUP004 | K9: 0.15 | L9: USD | M9: =IF(B9="","",MIN( IFERROR(E9*VLOOKUP(F9,Settings!$A$5:$C$10,3,FALSE()),9999999), IFERROR(H9*VLOOKUP(I9,Settings!$A$5:$C$10,3,FALSE()),9999999), IFERROR(K9*VLOOKUP(L9,Settings!$A$5:$C$10,3,FALSE()),9999999))) -> 0.1104 | N9: =IF(B9="","",IF(M9=E9*VLOOKUP(F9,Settings!$A$5:$C$10,3,FALSE()),D9, IF(M9=H9*VLOOKUP(I9,Settings!$A$5:$C$10,3,FALSE()),G9,J9))) -> SUP001 | O9: EA | Q9: =IF(B9="","",M9*O9) -> #VALUE! | R9: =IF(N9="","",IFERROR(VLOOKUP(N9,Suppliers!$A$4:$E$20,5,FALSE()),"-")) -> 21
A10: 5 | B10: ELC-001 | C10: Capacitor 100uF | D10: SUP005 | E10: 25 | F10: JPY | G10: SUP002 | H10: 0.18 | I10: EUR | J10: SUP004 | K10: 0.22 | L10: USD | M10: =IF(B10="","",MIN( IFERROR(E10*VLOOKUP(F10,Settings!$A$5:$C$10,3,FALSE()),9999999), IFERROR(H10*VLOOKUP(I10,Settings!$A$5:$C$10,3,FALSE()),9999999), IFERROR(K10*VLOOKUP(L10,Settings!$A$5:$C$10,3,FALSE()),9999999))) -> 0.1675 | N10: =IF(B10="","",IF(M10=E10*VLOOKUP(F10,Settings!$A$5:$C$10,3,FALSE()),D10, IF(M10=H10*VLOOKUP(I10,Settings!$A$5:$C$10,3,FALSE()),G10,J10))) -> SUP005 | O10: EA | Q10: =IF(B10="","",M10*O10) -> #VALUE! | R10: =IF(N10="","",IFERROR(VLOOKUP(N10,Suppliers!$A$4:$E$20,5,FALSE()),"-")) -> 18
A11: 6 | M11: =IF(B11="","",MIN( IFERROR(E11*VLOOKUP(F11,Settings!$A$5:$C$10,3,FALSE()),9999999), IFERROR(H11*VLOOKUP(I11,Settings!$A$5:$C$10,3,FALSE()),9999999), IFERROR(K11*VLOOKUP(L11,Settings!$A$5:$C$10,3,FALSE()),9999999))) | N11: =IF(B11="","",IF(M11=E11*VLOOKUP(F11,Settings!$A$5:$C$10,3,FALSE()),D11, IF(M11=H11*VLOOKUP(I11,Settings!$A$5:$C$10,3,FALSE()),G11,J11))) | Q11: =IF(B11="","",M11*O11) | R11: =IF(N11="","",IFERROR(VLOOKUP(N11,Suppliers!$A$4:$E$20,5,FALSE()),"-"))
A12: 7 | M12: =IF(B12="","",MIN( IFERROR(E12*VLOOKUP(F12,Settings!$A$5:$C$10,3,FALSE()),9999999), IFERROR(H12*VLOOKUP(I12,Settings!$A$5:$C$10,3,FALSE()),9999999), IFERROR(K12*VLOOKUP(L12,Settings!$A$5:$C$10,3,FALSE()),9999999))) | N12: =IF(B12="","",IF(M12=E12*VLOOKUP(F12,Settings!$A$5:$C$10,3,FALSE()),D12, IF(M12=H12*VLOOKUP(I12,Settings!$A$5:$C$10,3,FALSE()),G12,J12))) | Q12: =IF(B12="","",M12*O12) | R12: =IF(N12="","",IFERROR(VLOOKUP(N12,Suppliers!$A$4:$E$20,5,FALSE()),"-"))
A13: 8 | M13: =IF(B13="","",MIN( IFERROR(E13*VLOOKUP(F13,Settings!$A$5:$C$10,3,FALSE()),9999999), IFERROR(H13*VLOOKUP(I13,Settings!$A$5:$C$10,3,FALSE()),9999999), IFERROR(K13*VLOOKUP(L13,Settings!$A$5:$C$10,3,FALSE()),9999999))) | N13: =IF(B13="","",IF(M13=E13*VLOOKUP(F13,Settings!$A$5:$C$10,3,FALSE()),D13, IF(M13=H13*VLOOKUP(I13,Settings!$A$5:$C$10,3,FALSE()),G13,J13))) | Q13: =IF(B13="","",M13*O13) | R13: =IF(N13="","",IFERROR(VLOOKUP(N13,Suppliers!$A$4:$E$20,5,FALSE()),"-"))
A15: TOTAL BOM COST: | Q15: =SUM(Q6:Q14) -> #VALUE!

Sheet Labor
A1: 👷 DIRECT LABOR COSTS
A3: Select SKU: | B3: SKU-001
A5: LABOR RATE TABLE
A6: Labor Category | B6: Hourly Rate (USD) | C6: Burden Rate % | D6: Fully Loaded Rate
A7: Assembly - Basic | B7: 18 | C7: 0.35 | D7: =B7*(1+C7) -> 24.3
A8: Assembly - Skilled | B8: 25 | C8: 0.35 | D8: =B8*(1+C8) -> 33.75
A9: Machining - CNC | B9: 35 | C9: 0.4 | D9: =B9*(1+C9) -> 49
A10: Machining - Manual | B10: 28 | C10: 0.38 | D10: =B10*(1+C10) -> 38.64
A11: Welding | B11: 32 | C11: 0.42 | D11: =B11*(1+C11) -> 45.44
A12: Quality Inspection | B12: 24 | C12: 0.3 | D12: =B12*(1+C12) -> 31.2
A13: Packaging | B13: 15 | C13: 0.32 | D13: =B13*(1+C13) -> 19.8
A16: LABOR OPERATIONS FOR SELECTED SKU
A17: Op # | B17: Operation Description | C17: Labor Category | D17: Setup Time (hrs) | E17: Run Time (hrs/unit) | F17: Batch Size | G17: Total Hours | H17: Labor Cost
A18: 10 | B18: Material Preparation | C18: Assembly - Basic | D18: 0.5 | E18: 0.02 | F18: =Products!$E$4 -> 100 | G18: =D18+(E18*F18) -> 2.5 | H18: =G18*IFERROR(VLOOKUP(C18,$A$7:$D$13,4,FALSE()),0) -> 60.75
A19: 20 | B19: CNC Machining - Primary | C19: Machining - CNC | D19: 1 | E19: 0.15 | F19: =Products!$E$4 -> 100 | G19: =D19+(E19*F19) -> 16 | H19: =G19*IFERROR(VLOOKUP(C19,$A$7:$D$13,4,FALSE()),0) -> 784
A20: 30 | B20: CNC Machining - Secondary | C20: Machining - CNC | D20: 0.75 | E20: 0.1 | F20: =Products!$E$4 -> 100 | G20: =D20+(E20*F20) -> 10.75 | H20: =G20*IFERROR(VLOOKUP(C20,$A$7:$D$13,4,FALSE()),0) -> 526.75
A21: 40 | B21: Manual Finishing | C21: Machining - Manual | D21: 0.25 | E21: 0.05 | F21: =Products!$E$4 -> 100 | G21: =D21+(E21*F21) -> 5.25 | H21: =G21*IFERROR(VLOOKUP(C21,$A$7:$D$13,4,FALSE()),0) -> 202.86
A22: 50 | B22: Assembly | C22: Assembly - Skilled | D22: 0.5 | E22: 0.08 | F22: =Products!$E$4 -> 100 | G22: =D22+(E22*F22) -> 8.5 | H22: =G22*IFERROR(VLOOKUP(C22,$A$7:$D$13,4,FALSE()),0) -> 286.875
A23: 60 | B23: Quality Check | C23: Quality Inspection | D23: 0.25 | E23: 0.03 | F23: =Products!$E$4 -> 100 | G23: =D23+(E23*F23) -> 3.25 | H23: =G23*IFERROR(VLOOKUP(C23,$A$7:$D$13,4,FALSE()),0) -> 101.4
A24: 70 | B24: Packaging | C24: Packaging | D24: 0.15 | E24: 0.02 | F24: =Products!$E$4 -> 100 | G24: =D24+(E24*F24) -> 2.15 | H24: =G24*IFERROR(VLOOKUP(C24,$A$7:$D$13,4,FALSE()),0) -> 42.57
A26: TOTAL LABOR: | H26: =SUM(H18:H25) -> 2005.205
A27: LABOR COST PER UNIT: | H27: =IFERROR(H26/Products!$E$4,0) -> 20.05205

Sheet Machines
A1: ⚙️ MACHINE & EQUIPMENT COSTS
A3: Select SKU: | B3: SKU-001
A5: MACHINE RATE TABLE
A6: Machine ID | B6: Machine Name | C6: Hourly Rate | D6: Setup Cost | E6: Depreciation/hr | F6: Maintenance/hr | G6: Total Rate
A7: MCH-001 | B7: CNC Lathe - 3 Axis | C7: 45 | D7: 150 | E7: 8 | F7: 5 | G7: =C7+E7+F7 -> 58
A8: MCH-002 | B8: CNC Mill - 5 Axis | C8: 85 | D8: 250 | E8: 15 | F8: 8 | G8: =C8+E8+F8 -> 108
A9: MCH-003 | B9: Laser Cutter | C9: 55 | D9: 100 | E9: 10 | F9: 4 | G9: =C9+E9+F9 -> 69
A10: MCH-004 | B10: Press Brake | C10: 35 | D10: 75 | E10: 5 | F10: 3 | G10: =C10+E10+F10 -> 43
A11: MCH-005 | B11: Welding Station | C11: 25 | D11: 50 | E11: 3 | F11: 2 | G11: =C11+E11+F11 -> 30
A12: MCH-006 | B12: Assembly Station | C12: 15 | D12: 25 | E12: 2 | F12: 1 | G12: =C12+E12+F12 -> 18
A15: MACHINE OPERATIONS FOR SELECTED SKU
A16: Op # | B16: Operation | C16: Machine ID | D16: Setup Time (hrs) | E16: Cycle Time (hrs/unit) | F16: Batch Size | G16: Setup Cost | H16: Run Cost | I16: Total Cost
A17: 20 | B17: Primary Turning | C17: MCH-001 | D17: 1 | E17: 0.12 | F17: =Products!$E$4 -> 100 | G17: =IFERROR(VLOOKUP(C17,$A$7:$D$12,4,FALSE()),0) -> 150 | H17: =E17*F17*IFERROR(VLOOKUP(C17,$A$7:$G$12,7,FALSE()),0) -> 696 | I17: =G17+H17 -> 846
A18: 30 | B18: 5-Axis Milling | C18: MCH-002 | D18: 1.5 | E18: 0.18 | F18: =Products!$E$4 -> 100 | G18: =IFERROR(VLOOKUP(C18,$A$7:$D$12,4,FALSE()),0) -> 250 | H18: =E18*F18*IFERROR(VLOOKUP(C18,$A$7:$G$12,7,FALSE()),0) -> 1944 | I18: =G18+H18 -> 2194
A19: 35 | B19: Laser Marking | C19: MCH-003 | D19: 0.25 | E19: 0.02 | F19: =Products!$E$4 -> 100 | G19: =IFERROR(VLOOKUP(C19,$A$7:$D$12,4,FALSE()),0) -> 100 | H19: =E19*F19*IFERROR(VLOOKUP(C19,$A$7:$G$12,7,FALSE()),0) -> 138 | I19: =G19+H19 -> 238
A20: 55 | B20: Assembly Fixturing | C20: MCH-006 | D20: 0.5 | E20: 0.05 | F20: =Products!$E$4 -> 100 | G20: =IFERROR(VLOOKUP(C20,$A$7:$D$12,4,FALSE()),0) -> 25 | H20: =E20*F20*IFERROR(VLOOKUP(C20,$A$7:$G$12,7,FALSE()),0) -> 90 | I20: =G20+H20 -> 115
A23: TOTAL MACHINE COST: | I23: =SUM(I17:I22) -> 3393
A24: MACHINE COST PER UNIT: | I24: =IFERROR(I23/Products!$E$4,0) -> 33.93

Sheet Tooling
A1: 🔧 TOOLING & SETUP COSTS
A3: Select SKU: | B3: SKU-001 | D3: Expected Production Volume: | E3: 5000
A5: NON-RECURRING ENGINEERING (NRE) COSTS
A6: Item | B6: Description | C6: Cost | D6: Amortized Qty | E6: Cost/Unit
A7: Design Engineering | B7: CAD/CAM programming | C7: 2500 | D7: =$E$3 -> 5000 | E7: =IFERROR(C7/D7,0) -> 0.5
A8: Fixture Design | B8: Custom workholding | C8: 1500 | D8: =$E$3 -> 5000 | E8: =IFERROR(C8/D8,0) -> 0.3
A9: Prototype Tooling | B9: Initial samples | C9: 3000 | D9: =$E$3 -> 5000 | E9: =IFERROR(C9/D9,0) -> 0.6
A10: Testing & Validation | B10: First article inspection | C10: 800 | D10: =$E$3 -> 5000 | E10: =IFERROR(C10/D10,0) -> 0.16
A12: Total NRE: | C12: =SUM(C7:C11) -> 7800 | E12: =SUM(E7:E11) -> 1.56
A15: RECURRING TOOLING COSTS
A16: Tool Type | B16: Description | C16: Unit Cost | D16: Tool Life (units) | E16: Cost/Unit
A17: Cutting Inserts | B17: Carbide inserts for lathe | C17: 25 | D17: 500 | E17: =IFERROR(C17/D17,0) -> 0.05
A18: End Mills | B18: Solid carbide end mills | C18: 85 | D18: 1000 | E18: =IFERROR(C18/D18,0) -> 0.085
A19: Drill Bits | B19: Coated HSS drills | C19: 15 | D19: 2000 | E19: =IFERROR(C19/D19,0) -> 0.0075
A20: Taps | B20: Thread forming taps | C20: 35 | D20: 1500 | E20: =IFERROR(C20/D20,0) -> 0.023333333
A22: Total Recurring Tooling/Unit: | E22: =SUM(E17:E21) -> 0.16583333
A24: TOTAL TOOLING COST PER UNIT: | E24: =E12+E22 -> 1.7258333

Sheet Quality
A1: ✅ QUALITY & INSPECTION COSTS
A3: Select SKU: | B3: SKU-001
A5: Inspection Type | B5: Description | C5: Method | D5: Time (min/unit) | E5: Hourly Rate | F5: Cost/Unit | G5: % of Units | H5: Effective Cost/Unit
A6: Incoming | B6: Material verification | C6: Visual + Cert | D6: 2 | E6: 24 | F6: =(D6/60)*E6 -> 0.8 | G6: 1 | H6: =F6*G6 -> 0.8
A7: First Article | B7: Initial setup validation | C7: CMM | D7: 30 | E7: 45 | F7: =(D7/60)*E7 -> 22.5 | G7: 0.02 | H7: =F7*G7 -> 0.45
A8: In-Process | B8: Dimensional checks | C8: Go/No-Go | D8: 3 | E8: 24 | F8: =(D8/60)*E8 -> 1.2 | G8: 0.2 | H8: =F8*G8 -> 0.24
A9: Final | B9: Complete inspection | C9: CMM + Visual | D9: 10 | E9: 35 | F9: =(D9/60)*E9 -> 5.8333333 | G9: 1 | H9: =F9*G9 -> 5.8333333
A10: Packaging | B10: Packaging verification | C10: Visual | D10: 1 | E10: 18 | F10: =(D10/60)*E10 -> 0.3 | G10: 1 | H10: =F10*G10 -> 0.3
A13: CERTIFICATION & DOCUMENTATION
A14: Item | B14: Description | C14: Cost | D14: Per Batch Size | E14: Cost/Unit
A15: Certificate of Conformance | B15: CoC documentation | C15: 25 | D15: 100 | E15: =IFERROR(C15/D15,0) -> 0.25
A16: Material Certs | B16: Mill test reports | C16: 15 | D16: 100 | E16: =IFERROR(C16/D16,0) -> 0.15
A17: Test Reports | B17: Inspection data package | C17: 50 | D17: 100 | E17: =IFERROR(C17/D17,0) -> 0.5
A20: TOTAL QUALITY COST PER UNIT: | H20: =SUM(H6:H11)+SUM(E15:E18) -> 8.5233333

Sheet Packaging
A1: 📦 PACKAGING COSTS
A3: Select SKU: | B3: SKU-001
A5: UNIT PACKAGING
A6: Item | B6: Description | C6: Unit Cost | D6: Qty/Unit | E6: Cost/Unit
A7: Individual Box | B7: Corrugated box 10x8x6 | C7: 0.85 | D7: 1 | E7: =C7*D7 -> 0.85
A8: Inner Foam | B8: PE foam insert | C8: 0.35 | D8: 1 | E8: =C8*D8 -> 0.35
A9: Desiccant | B9: Silica gel packet | C9: 0.05 | D9: 2 | E9: =C9*D9 -> 0.1
A10: Poly Bag | B10: Anti-static bag | C10: 0.12 | D10: 1 | E10: =C10*D10 -> 0.12
A11: Label | B11: Product identification | C11: 0.08 | D11: 1 | E11: =C11*D11 -> 0.08
A12: Documentation | B12: User manual/warranty | C12: 0.25 | D12: 1 | E12: =C12*D12 -> 0.25
A14: Total Unit Packaging: | E14: =SUM(E7:E13) -> 1.75
A17: MASTER CARTON PACKAGING
A18: Item | B18: Description | C18: Cost | D18: Units/Carton | E18: Cost/Unit
A19: Master Carton | B19: Heavy duty box | C19: 2.5 | D19: 10 | E19: =IFERROR(C19/D19,0) -> 0.25
A20: Pallet Wrap | B20: Stretch film | C20: 1.2 | D20: 100 | E20: =IFERROR(C20/D20,0) -> 0.012
A21: Corner Protectors | B21: Cardboard corners | C21: 0.8 | D21: 100 | E21: =IFERROR(C21/D21,0) -> 0.008
A22: Pallet | B22: Wooden pallet (prorated) | C22: 8 | D22: 200 | E22: =IFERROR(C22/D22,0) -> 0.04
A24: Total Master Carton/Unit: | E24: =SUM(E19:E23) -> 0.31
A26: TOTAL PACKAGING COST PER UNIT: | E26: =E14+E24 -> 2.06

Sheet Logistics
A1: 🚚 SHIPPING & LOGISTICS COSTS
A3: Select SKU: | B3: SKU-001 | D3: Shipment Quantity: | E3: 100
A5: PRODUCT SPECIFICATIONS
A6: Unit Weight (kg): | B6: 2.5
A7: Unit Volume (m³): | B7: 0.005
A8: Units per Carton: | B8: 10
A9: Carton Weight (kg): | B9: 28
A10: Carton Dimensions (cm): | B10: 50x40x30
A13: FREIGHT OPTIONS
A14: Mode | B14: Origin | C14: Destination | D14: Transit Days | E14: Rate/kg | F14: Min Charge | G14: Total Freight | H14: Cost/Unit
A15: Sea Freight (FCL) | B15: Shanghai, CN | C15: Los Angeles, US | D15: 25 | E15: 0.08 | F15: 1500 | G15: =MAX(E15*$B$6*$E$3,F15) -> 1500 | H15: =IFERROR(G15/$E$3,0) -> 15
A16: Sea Freight (LCL) | B16: Shanghai, CN | C16: Los Angeles, US | D16: 30 | E16: 0.15 | F16: 150 | G16: =MAX(E16*$B$6*$E$3,F16) -> 150 | H16: =IFERROR(G16/$E$3,0) -> 1.5
A17: Air Freight | B17: Shanghai, CN | C17: Los Angeles, US | D17: 5 | E17: 4.5 | F17: 100 | G17: =MAX(E17*$B$6*$E$3,F17) -> 1125 | H17: =IFERROR(G17/$E$3,0) -> 11.25
A18: Air Express | B18: Shanghai, CN | C18: Los Angeles, US | D18: 3 | E18: 8 | F18: 50 | G18: =MAX(E18*$B$6*$E$3,F18) -> 2000 | H18: =IFERROR(G18/$E$3,0) -> 20
A19: Ground (Domestic) | B19: Los Angeles, US | C19: Chicago, US | D19: 5 | E19: 0.25 | F19: 25 | G19: =MAX(E19*$B$6*$E$3,F19) -> 62.5 | H19: =IFERROR(G19/$E$3,0) -> 0.625
A22: ADDITIONAL LOGISTICS COSTS
A23: Item | B23: Description | C23: Cost | D23: Per Qty | E23: Cost/Unit
A24: Customs Clearance | B24: Import documentation | C24: 150 | D24: =$E$3 -> 100 | E24: =IFERROR(C24/D24,C24) -> 1.5
A25: Duties & Tariffs | B25: Import duties @ 5% | C25: =BOM!Q15*0.05 -> #VALUE! | D25: =$E$3 -> 100 | E25: =IFERROR(C25/D25,C25) -> #VALUE!
A26: Insurance | B26: Cargo insurance | C26: =BOM!Q15*0.01 -> #VALUE! | D26: =$E$3 -> 100 | E26: =IFERROR(C26/D26,C26) -> #VALUE!
A27: Handling | B27: Warehouse handling | C27: 0.5 | D27: 1 | E27: =IFERROR(C27/D27,C27) -> 0.5
A30: SELECTED FREIGHT MODE: | B30: Sea Freight (LCL)
A31: TOTAL LOGISTICS COST PER UNIT: | E31: =IFERROR(VLOOKUP(B30,A15:H19,8,FALSE()),0)+SUM(E24:E28) -> #VALUE!

Sheet Cost Summary
A1: 📊 COST SUMMARY & ANALYSIS
A3: Selected SKU: | B3: SKU-001 | C3: Product: | D3: =IFERROR(VLOOKUP(B3,Products!A:B,2,FALSE()),"-") -> Precision Gear Assembly | E3: Batch Size: | F3: =Products!$E$4 -> 100
A5: COST BREAKDOWN
A6: Cost Category | B6: Total Batch Cost | C6: Cost Per Unit | D6: % of Total
A7: Raw Materials (BOM) | B7: =BOM!Q15 -> #VALUE! | C7: =IFERROR(B7/F3,0) -> 0 | D7: =IFERROR(C7/$C$14,0) -> 0
A8: Direct Labor | B8: =Labor!H26 -> 2005.205 | C8: =Labor!H27 -> 20.05205 | D8: =IFERROR(C8/$C$14,0) -> 0
A9: Machine Costs | B9: =Machines!I23 -> 3393 | C9: =Machines!I24 -> 33.93 | D9: =IFERROR(C9/$C$14,0) -> 0
A10: Tooling & Setup | B10: =Tooling!E24*F3 -> 172.58333 | C10: =Tooling!E24 -> 1.7258333 | D10: =IFERROR(C10/$C$14,0) -> 0
A11: Quality & Inspection | B11: =Quality!H20*F3 -> 852.33333 | C11: =Quality!H20 -> 8.5233333 | D11: =IFERROR(C11/$C$14,0) -> 0
A12: Packaging | B12: =Packaging!E26*F3 -> 206 | C12: =Packaging!E26 -> 2.06 | D12: =IFERROR(C12/$C$14,0) -> 0
A13: Logistics (per unit) | B13: =Logistics!E31*F3 -> #VALUE! | C13: =Logistics!E31 -> #VALUE! | D13: =IFERROR(C13/$C$14,0) -> 0
A14: TOTAL DIRECT COST | B14: =SUM(B7:B13) -> #VALUE! | C14: =SUM(C7:C13) -> #VALUE! | D14: =SUM(D7:D13) -> 0
A16: OVERHEAD ALLOCATION
A17: Factory Overhead | B17: =Settings!C25*Labor!H26 -> 1704.4243 | C17: =IFERROR(B17/F3,0) -> 17.044242
A18: Administrative | B18: =Settings!C26*B14 -> #VALUE! | C18: =IFERROR(B18/F3,0) -> 0
A19: Engineering Support | B19: =Settings!C27*Labor!H26 -> 300.78075 | C19: =IFERROR(B19/F3,0) -> 3.0078075
A20: TOTAL OVERHEAD | B20: =SUM(B17:B19) -> #VALUE! | C20: =SUM(C17:C19) -> 20.05205
A22: TOTAL MANUFACTURING COST | B22: =B14+B20 -> #VALUE! | C22: =C14+C20 -> #VALUE!
A25: PRICING CALCULATOR
A26: Order Quantity: | B26: 100
A27: Markup Tier: | B27: =IF(B26<=100,"Tier 1",IF(B26<=500,"Tier 2",IF(B26<=1000,"Tier 3","Tier 4"))) -> Tier 1
A28: Markup %: | B28: =IFERROR(VLOOKUP(B27,Settings!A17:C20,3,FALSE()),0) -> 0
A30: UNIT SELLING PRICE: | B30: =C22*(1+B28) -> #VALUE!
A31: GROSS PROFIT/UNIT: | B31: =B30-C22 -> #VALUE!
A32: GROSS MARGIN %: | B32: =IFERROR(B31/B30,0) -> 0

Sheet Quote
A1: 📋 CUSTOMER QUOTATION
A3: QUOTE INFORMATION | D3: CUSTOMER INFORMATION
A4: Quote Number: | B4: Q-2024-001 | D4: Company Name:
A5: Quote Date: | B5: 2026-01-19 | D5: Contact Person:
A6: Valid Until: | D6: Email:
A7: Revision: | B7: 1 | D7: Phone:
A8: Prepared By: | D8: Address:
A11: QUOTED ITEMS
A12: Line | B12: SKU | C12: Description | D12: Quantity | E12: Unit Price | F12: Extended Price | G12: Lead Time | H12: Notes
A13: 1 | B13: SKU-001 | C13: =IFERROR(VLOOKUP(B13,Products!A:B,2,FALSE()),"") -> Precision Gear Assembly | D13: 100 | E13: ="Cost Summary"!B30 -> #VALUE! | F13: =IFERROR(D13*E13,0) -> 0 | G13: 4-6 weeks
A14: 2 | C14: =IFERROR(VLOOKUP(B14,Products!A:B,2,FALSE()),"") | F14: =IFERROR(D14*E14,0) -> 0
A15: 3 | C15: =IFERROR(VLOOKUP(B15,Products!A:B,2,FALSE()),"") | F15: =IFERROR(D15*E15,0) -> 0
A16: 4 | C16: =IFERROR(VLOOKUP(B16,Products!A:B,2,FALSE()),"") | F16: =IFERROR(D16*E16,0) -> 0
A17: 5 | C17: =IFERROR(VLOOKUP(B17,Products!A:B,2,FALSE()),"") | F17: =IFERROR(D17*E17,0) -> 0
A18: 6 | C18: =IFERROR(VLOOKUP(B18,Products!A:B,2,FALSE()),"") | F18: =IFERROR(D18*E18,0) -> 0
A19: 7 | C19: =IFERROR(VLOOKUP(B19,Products!A:B,2,FALSE()),"") | F19: =IFERROR(D19*E19,0) -> 0
A20: 8 | C20: =IFERROR(VLOOKUP(B20,Products!A:B,2,FALSE()),"") | F20: =IFERROR(D20*E20,0) -> 0
A21: 9 | C21: =IFERROR(VLOOKUP(B21,Products!A:B,2,FALSE()),"") | F21: =IFERROR(D21*E21,0) -> 0
A22: 10 | C22: =IFERROR(VLOOKUP(B22,Products!A:B,2,FALSE()),"") | F22: =IFERROR(D22*E22,0) -> 0
A24: SUBTOTAL: | F24: =SUM(F13:F22) -> 0
A25: Shipping & Handling: | F25: 0
A26: Tax (if applicable): | F26: 0
A27: TOTAL: | F27: =SUM(F24:F26) -> 0
A30: TERMS & CONDITIONS
A31: 1. Payment Terms: Net 30 days from invoice date
A32: 2. Delivery: FOB Origin unless otherwise specified
A33: 3. Validity: This quote is valid for 30 days from date of issue
A34: 4. Prices: Subject to change based on raw material costs
A35: 5. Minimum Order: As specified per line item
A36: 6. Tooling: NRE charges may apply for new products
A40: REVISION HISTORY
A41: Rev | B41: Date | C41: Description | D41: By
A42: 1 | B42: 2026-01-19 | C42: Initial quote
