Workbook

Sheet Dashboard Overview
A1: PRODUCT COSTING DASHBOARD | H1: Date: 2026-01-19
A3: Product Selection | B3: Select Product | C3: Product A | E3: Quick Navigation
E4: → Material Costs
A5: Metric | B5: Value | C5: Status | E5: → Labor Costs
A6: Total Manufacturing Cost | B6: 0 | E6: → Overhead Costs
A7: Suggested Retail Price | B7: 0 | E7: → Logistics Costs
A8: Profit Margin % | B8: 0 | E8: → Cost Summary
A9: Material Cost | B9: 0 | E9: → Historical Analysis
A10: Labor Cost | B10: 0
A11: Overhead Cost | B11: 0
A12: Cost Category | B12: Amount
A13: Materials | B13: 0
A14: Labor | B14: 0
A15: Overhead | B15: 0
A16: Logistics | B16: 0

Sheet Material Costs
A1: MATERIAL COSTS
A3: Enter material details below. Formulas will calculate totals automatically.
A5: Item # | B5: Material Description | C5: Supplier | D5: Unit | E5: Quantity | F5: Unit Cost | G5: Total Cost | H5: Notes
A6: 1 | B6: Raw Material Alpha | C6: Supplier A | D6: kg | E6: 100 | F6: 5.5 | G6: =E6*F6
A7: 2 | B7: Component Beta | C7: Supplier B | D7: pcs | E7: 250 | F7: 2.75 | G7: =E7*F7
A8: 3 | B8: Packaging Material | C8: Supplier C | D8: pcs | E8: 500 | F8: 0.5 | G8: =E8*F8
A9: 4 | B9: Chemical Additive | C9: Supplier A | D9: liters | E9: 25 | F9: 12 | G9: =E9*F9
A10: 5 | B10: Fasteners Set | C10: Supplier D | D10: pcs | E10: 1000 | F10: 0.15 | G10: =E10*F10
A25: MATERIAL COST SUMMARY
A26: Category | B26: Total Cost | C26: % of Materials
A27: Raw Materials | B27: =SUM(G6:G50) | C27: =IF(B26>0,G26/B27,0)
A28: Components | B28: 0 | C28: 0
A29: Packaging | B29: 0 | C29: 0
A30: Consumables | B30: 0 | C30: 0
A31: TOTAL MATERIALS | B31: =SUM(B26:B29) | C31: 100%

Sheet Labor Costs
A1: LABOR COSTS
A3: Labor Category | B3: Hourly Rate ($) | C3: Hours/Unit | D3: Total Cost/Unit | E3: Notes
A6: Direct Labor - Assembly | B6: 25 | C6: 2.5 | D6: =B6*C6
A7: Direct Labor - Testing | B7: 28 | C7: 0.5 | D7: =B7*C7
A8: Indirect Labor - Supervision | B8: 35 | C8: 0.25 | D8: =B8*C8
A9: Quality Assurance | B9: 30 | C9: 0.75 | D9: =B9*C9
A10: Setup Labor | B10: 27 | C10: 0.5 | D10: =B10*C10
A20: LABOR COST SUMMARY
A21: Total Labor Cost per Unit | B21: =SUM(D6:D50)

Sheet Overhead Costs
A1: OVERHEAD COSTS
A3: Allocation Method: | B3: Direct Labor Hours
A5: Overhead Item | B5: Category | C5: Total Cost ($) | D5: Allocation Rate
A6: Factory Rent | B6: Production | C6: 15000 | D6: =IF($B$3="Direct Labor Hours",C6/100,0)
A7: Utilities | B7: Production | C7: 3500 | D7: =IF($B$3="Direct Labor Hours",C7/100,0)
A8: Equipment Depreciation | B8: Production | C8: 8000 | D8: =IF($B$3="Direct Labor Hours",C8/100,0)
A9: Maintenance | B9: Production | C9: 2500 | D9: =IF($B$3="Direct Labor Hours",C9/100,0)
A10: Insurance | B10: Facility | C10: 1200 | D10: =IF($B$3="Direct Labor Hours",C10/100,0)
A11: Supervision | B11: Administrative | C11: 5000 | D11: =IF($B$3="Direct Labor Hours",C11/100,0)
A18: OVERHEAD ALLOCATION
A20: Total Overhead Costs | B20: =SUM(C6:C50)
A21: Allocated Overhead per Unit | B21: =B20/100

Sheet Logistics Costs
A1: LOGISTICS COSTS
A3: Inbound Logistics
A5: Description | B5: Type | C5: Carrier | D5: Origin | E5: Destination | F5: Cost ($) | G5: Cost/Unit
A6: Sea Freight (20ft) | B6: Sea | C6: Carrier A | D6: Shanghai | E6: Los Angeles | F6: 2500 | G6: =F6/100
A7: Air Freight | B7: Air | C7: Carrier B | D7: Hong Kong | E7: New York | F7: 4500 | G7: =F7/100
A8: Trucking - Local | B8: Road | C8: Carrier C | D8: Warehouse | E8: Factory | F8: 350 | G8: =F8/100
A9: Customs & Duties | B9: Other | C9: - | D9: Port | E9: Warehouse | F9: 800 | G9: =F9/100
A15: Outbound Logistics
A17: Description | B17: Type | C17: Carrier | D17: Origin | E17: Destination | F17: Cost ($) | G17: Cost/Unit
A19: Domestic Shipping | B19: Road | C19: Carrier D | D19: Factory | E19: Customer | F19: 150 | G19: =F19/100
A20: International Air | B20: Air | C20: Carrier B | D20: Factory | E20: Customer | F20: 3200 | G20: =F20/100
A26: LOGISTICS SUMMARY
A28: Total Inbound Costs | B28: =SUM(F6:F14)
A29: Total Outbound Costs | B29: =SUM(F19:F25)
A30: Total Logistics Cost | B30: =B28+B29

Sheet Cost Summary
A1: COST SUMMARY
A3: Product | B3: Materials | C3: Labor | D3: Overhead | E3: Logistics | F3: Total Cost | G3: Margin %
A5: Product A | B5: ='Material Costs'!B31 | C5: ='Labor Costs'!$B$21 | D5: ='Overhead Costs'!$B$21 | E5: ='Logistics Costs'!$B$30 | F5: =SUM(B5:E5) | G5: 0.25
A6: Product B | B6: ='Material Costs'!B32 | C6: ='Labor Costs'!$B$21 | D6: ='Overhead Costs'!$B$21 | E6: ='Logistics Costs'!$B$30 | F6: =SUM(B6:E6) | G6: 0.25
A7: Product C | B7: ='Material Costs'!B32 | C7: ='Labor Costs'!$B$21 | D7: ='Overhead Costs'!$B$21 | E7: ='Logistics Costs'!$B$30 | F7: =SUM(B7:E7) | G7: 0.25
A9: PRICING RECOMMENDATIONS
A10: Markup Percentage: | B10: 0.4
A11: Product | B11: Total Cost | C11: Markup ($) | D11: Suggested Price
A12: Product A | B12: =F5 | C12: =B12*$B$10 | D12: =B12+C12
A13: Product B | B13: =F6 | C13: =B13*$B$10 | D13: =B13+C13
A14: Product C | B14: =F7 | C14: =B14*$B$10 | D14: =B14+C14

Sheet Historical Analysis
A1: COST HISTORY ANALYSIS
A3: Monthly Cost Tracking
A5: Period | B5: Materials | C5: Labor | D5: Overhead | E5: Logistics | F5: Total
A6: 2025-01 | B6: 0 | C6: 0 | D6: 0 | E6: 0
A7: 2025-02 | B7: 0 | C7: 0 | D7: 0 | E7: 0
A8: 2025-03 | B8: 0 | C8: 0 | D8: 0 | E8: 0
A9: 2025-04 | B9: 0 | C9: 0 | D9: 0 | E9: 0
A10: 2025-05 | B10: 0 | C10: 0 | D10: 0 | E10: 0
A11: 2025-06 | B11: 0 | C11: 0 | D11: 0 | E11: 0
A12: 2025-07 | B12: 0 | C12: 0 | D12: 0 | E12: 0
A13: 2025-08 | B13: 0 | C13: 0 | D13: 0 | E13: 0
A14: 2025-09 | B14: 0 | C14: 0 | D14: 0 | E14: 0
A15: 2025-10 | B15: 0 | C15: 0 | D15: 0 | E15: 0
A16: 2025-11 | B16: 0 | C16: 0 | D16: 0 | E16: 0
A17: 2025-12 | B17: 0 | C17: 0 | D17: 0 | E17: 0
A18: TOTAL | B18: =SUM(B6:B17) | C18: =SUM(C6:C17) | D18: =SUM(D6:D17) | E18: =SUM(E6:E17) | F18: =SUM(F6:F17)

Sheet Quote Input
A1: QUOTATION GENERATOR
A3: Quotation Number: | B3: ="QT-"&TEXT(TODAY(),"YYYYMMDD")&"-"&TEXT(COUNTIF('Quotation History'!A:A,"*")+1,"000") | K3: Date: | L3: 2026-01-19
A4: Valid Until: | B4: =EDATE(L3,1) | K4: Salesperson:
A6: CUSTOMER INFORMATION
A7: Customer Name:
A8: Contact Person: | C8: Email:
A9: Billing Address:
A10: Shipping Address:
A11: Payment Terms:
A14: PRODUCT DETAILS
A16: Product Code | B16: Description | C16: Quantity | D16: Unit Price | E16: Discount % | F16: Unit Cost | G16: Line Total | H16: Margin % | I16: Delivery Date | J16: Notes
A17: Product A | B17: Industrial Component Alpha | C17: 100 | D17: 75 | E17: 0 | F17: 45 | G17: =C17*D17*(1-E17) | H17: 40
A18: Product B | B18: Industrial Component Beta | C18: 50 | D18: 120 | E18: 5 | F18: 72 | G18: =C18*D18*(1-E18) | H18: 40
A35: QUOTATION SUMMARY
A37: Subtotal: | B37: =SUM(G17:G30)
A38: Discount Amount: | B38: =SUMPRODUCT(C17:C30,D17:D30,E17:E30)
A39: Shipping & Handling: | B39: 0
A40: Tax (8.25%): | B40: =(B37-B38+B39)*0.0825
A41: GRAND TOTAL: | B41: =B37-B38+B39+B40
A42: Overall Margin: | B42: =(B41-SUMPRODUCT(C17:C30,F17:F30))/B41
A44: Notes:
A45: • Prices valid for 30 days from quotation date
A46: • Standard payment terms: Net 30
A47: • Lead time: 2-3 weeks after order confirmation
A48: • Shipping FOB Origin

Sheet Customer Database
A1: CUSTOMER DATABASE
A3: Customer Code | B3: Company Name | C3: Contact Person | D3: Email | E3: Phone | F3: Billing Address | G3: Payment Terms | H3: Credit Limit | I3: Discount % | J3: Customer Since
A5: CUST001 | B5: Acme Corporation | C5: John Smith | D5: jsmith@acme.com | E5: 555-0101 | F5: 123 Business Ave, New York, NY 10001 | G5: Net 30 | H5: 50000 | I5: 0 | J5: 2020-03-15
A6: CUST002 | B6: Global Industries | C6: Mary Johnson | D6: mjohnson@global.com | E6: 555-0102 | F6: 456 Commerce St, Chicago, IL 60601 | G6: Net 45 | H6: 75000 | I6: 5 | J6: 2019-08-22
A7: CUST003 | B7: Pacific Trading | C7: David Lee | D7: dlee@pacific.com | E7: 555-0103 | F7: 789 Harbor Blvd, San Francisco, CA 94102 | G7: Net 30 | H7: 60000 | I7: 0 | J7: 2021-01-10
A8: CUST004 | B8: Mountain Supply | C8: Sarah Davis | D8: sdavis@mountain.com | E8: 555-0104 | F8: 321 Alpine Way, Denver, CO 80202 | G8: Net 30 | H8: 40000 | I8: 2 | J8: 2020-11-05
A9: CUST005 | B9: Urban Solutions | C9: Michael Brown | D9: mbrown@urban.com | E9: 555-0105 | F9: 654 Metro Drive, Los Angeles, CA 90001 | G9: Net 45 | H9: 100000 | I9: 10 | J9: 2018-06-18

Sheet Product Database
A1: PRODUCT DATABASE
A3: Product Code | B3: Product Name | C3: Category | D3: Description | E3: Unit of Measure | F3: Min Order Qty | G3: Lead Time (days) | H3: Standard Cost | I3: Standard Price | J3: Volume Tier 1 | K3: Volume Tier 2
A5: PROD-A | B5: Industrial Component Alpha | C5: Components | D5: High-grade industrial component | E5: pcs | F5: 50 | G5: 14 | H5: 45 | I5: 75 | J5: 70 | K5: 65
A6: PROD-B | B6: Industrial Component Beta | C6: Components | D6: Standard industrial component | E6: pcs | F6: 25 | G6: 10 | H6: 72 | I6: 120 | J6: 115 | K6: 108
A7: PROD-C | B7: Raw Material Gamma | C7: Raw Materials | D7: Premium raw material | E7: kg | F7: 100 | G7: 21 | H7: 25 | I7: 42 | J7: 40 | K7: 38
A8: PROD-D | B8: Packaging Set Delta | C8: Packaging | D8: Complete packaging solution | E8: set | F8: 200 | G8: 7 | H8: 8 | I8: 15 | J8: 14 | K8: 13
A9: PROD-E | B9: Assembly Kit Epsilon | C9: Kits | D9: Pre-assembled component kit | E9: kit | F9: 10 | G9: 21 | H9: 180 | I9: 300 | J9: 285 | K9: 270

Sheet Quote Summary
A1: QUOTATION SUMMARY
A3: This sheet provides a quick overview of the current quotation.
A5: Quotation #: | B5: =IF(Quote Input!B3<>"",Quote Input!B3,"Not Generated")
A6: Customer: | B6: =IF(Quote Input!B7<>"",Quote Input!B7,"Not Selected")
A7: Total Items: | B7: =COUNTIF(Quote Input!A17:A30,"<>")
A8: Total Quantity: | B8: =SUM(Quote Input!C17:C30)
A9: Subtotal: | B9: =Quote Input!B37
A10: Grand Total: | B10: =Quote Input!B41
A12: APPROVAL STATUS
A13: Status: | B13: Draft
A14: Prepared By:
A15: Approved By:
A16: Approval Date:

Sheet Quote Print Layout
A1: QUOTATION
A2: YOUR COMPANY NAME | E2: QUOTATION # | F2: =IF(Quote Input!B3<>"",Quote Input!B3,"")
A3: 123 Business Street | E3: DATE | F3: =IF(Quote Input!L3<>"",Quote Input!L3,TODAY())
A4: City, State 12345 | E4: VALID UNTIL | F4: =IF(Quote Input!B4<>"",Quote Input!B4,EDATE(TODAY(),1))
A5: Phone: (555) 123-4567 | Email: info@yourcompany.com | E5: SALESREP | F5: =IF(Quote Input!L4<>"",Quote Input!L4,"")
A7: BILL TO: | E7: SHIP TO:
A8: =IF(Quote Input!B7<>"",Quote Input!B7,"Customer Name") | E8: =IF(Quote Input!B7<>"",Quote Input!B7,"Customer Name")
A9: =IF(Quote Input!B8<>"",Quote Input!B8,"") | E9: =IF(Quote Input!B10<>"",Quote Input!B10,"Shipping Address")
A10: =IF(Quote Input!B9<>"",Quote Input!B9,"Billing Address")
A12: QTY | B12: DESCRIPTION | C12: UNIT PRICE | D12: DISCOUNT | E12: LINE TOTAL | F12: DELIVERY
D25: Subtotal: | E25: =IF(Quote Input!B37<>"",Quote Input!B37,0)
D26: Tax: | E26: =IF(Quote Input!B40<>"",Quote Input!B40,0)
D27: TOTAL: | E27: =IF(Quote Input!B41<>"",Quote Input!B41,0)
A30: TERMS AND CONDITIONS
A31: 1. Prices are valid for 30 days from quotation date.
A32: 2. Payment terms: Net 30 days from invoice date.
A33: 3. Lead times commence upon receipt of purchase order and deposit.
A34: 4. All prices are FOB origin unless otherwise specified.
A35: 5. This quotation is subject to availability of materials.
A40: Accepted By: | E40: Authorized By:
A41: __________________________ | E41: __________________________
A42: Signature | E42: Your Company Representative
A43: Date: __________________ | E43: Date: __________________

Sheet Quotation History
A1: QUOTATION HISTORY
A3: Quote # | B3: Date | C3: Customer | D3: Items | E3: Quantity | F3: Total ($) | G3: Status | H3: Created By | I3: Won Date | J3: Lost Date | K3: Lost To | L3: Follow-up Date
A5: QT-20250115-001 | B5: 2025-01-15 | C5: Acme Corporation | D5: 2 | E5: 150 | F5: 12500 | G5: Won | H5: John Doe | I5: 2025-01-18
A6: QT-20250114-002 | B6: 2025-01-14 | C6: Global Industries | D6: 3 | E6: 75 | F6: 18900 | G6: Pending | H6: Jane Smith | L6: 2025-02-01
A7: QT-20250112-003 | B7: 2025-01-12 | C7: Pacific Trading | D7: 1 | E7: 200 | F7: 8400 | G7: Lost | H7: John Doe | J7: 2025-01-15 | K7: Competitor A
A8: QT-20250110-004 | B8: 2025-01-10 | C8: Mountain Supply | D8: 2 | E8: 100 | F8: 15600 | G8: Won | H8: Jane Smith | I8: 2025-01-12
A9: QT-20250108-005 | B9: 2025-01-08 | C9: Urban Solutions | D9: 4 | E9: 300 | F9: 45000 | G9: Expired | H9: John Doe | J9: 2025-02-08
A25: SUMMARY STATISTICS
A27: Total Quotes: | B27: =COUNTA(A5:A500)-1
A28: Quotes Won: | B28: =COUNTIF(G5:G500,"Won")
A29: Quotes Lost: | B29: =COUNTIF(G5:G500,"Lost")
A30: Win Rate: | B30: =IF(B27>0,B28/B27,0)
A31: Total Quoted Value: | B31: =SUM(F5:F500)
A32: Total Won Value: | B32: =SUMIF(G5:G500,"Won",F5:F500)
